speech_analytics/__init__.py
speech_analytics/models.py
speech_analytics/test1.json
speech_analytics-0.1.8.dist-info/WHEEL
speech_analytics-0.1.8.dist-info/METADATA
speech_analytics-0.1.8.dist-info/RECORD
