Metadata-Version: 2.1
Name: speech-analytics
Version: 0.1.8
Summary: 
Author: Ashleigh Richardson
Author-email: ashleigh.richardson@uqconnect.edu.au
Requires-Python: >=3.10,<4.0
Classifier: Programming Language :: Python :: 3
Classifier: Programming Language :: Python :: 3.10
Requires-Dist: happytransformer (>=2.4.1,<3.0.0)
Requires-Dist: spacy (>=3.4.1,<4.0.0)
